pyevents21/__init__.py
pyevents21/events.py
pyevents21-0.2.dist-info/METADATA
pyevents21-0.2.dist-info/WHEEL
pyevents21-0.2.dist-info/top_level.txt
pyevents21-0.2.dist-info/RECORD
