Metadata-Version: 2.1
Name: pyevents21
Version: 0.2
Summary: Pre Handle Events System
Home-page: https://github.com/SweetSmoke21/pyevents21
Author: Anosov Igor
Author-email: AnosovIgor404@gmail.com
License: UNKNOWN
Platform: UNKNOWN
Classifier: Programming Language :: Python :: 3.7
Classifier: License :: OSI Approved :: GNU General Public License v3 (GPLv3)
